DESCRIPTION.rst
MANIFEST.in
README.rst
setup.cfg
setup.py
Xymon_Class/Xymon.py
Xymon_Class/__init.py__
Xymon_Class/test.py
Xymon_Class.egg-info/PKG-INFO
Xymon_Class.egg-info/SOURCES.txt
Xymon_Class.egg-info/dependency_links.txt
Xymon_Class.egg-info/top_level.txt
tests/__init__.py
tests/test_simple.py