Metadata-Version: 1.0
Name: Xymon-Class
Version: 0.1.0
Summary: A simple Class to manipulate Xymon test script
Home-page: https://github.com/erikbeauvalot/Xymon_Class
Author: Erik Beauvalot
Author-email: erik@beauvalot.com
License: UNKNOWN
Platform: UNKNOWN
